{
  "$schema": "https://raw.githubusercontent.com/spdx/spdx-spec/v2.2.1/schemas/spdx-schema.json",
  "spdxVersion": "SPDX-2.2",
  "dataLicense": "CC0-1.0",
  "SPDXID": "SPDXRef-DOCUMENT",
  "documentNamespace": "https://spdx.org/spdxdocs/boost-tokenizer-x64-osx-1.83.0-3ef4122d-0b8e-4685-a18b-376be3d300af",
  "name": "boost-tokenizer:x64-osx@1.83.0 e2a9222c4641102f397f5eca33dfe55f6769eb7613fa7a9af4e394259a6d85fd",
  "creationInfo": {
    "creators": [
      "Tool: vcpkg-9990a4c9026811a312cb2af78bf77f3d9d288416"
    ],
    "created": "2023-09-24T15:23:43Z"
  },
  "relationships": [
    {
      "spdxElementId": "SPDXRef-port",
      "relationshipType": "GENERATES",
      "relatedSpdxElement": "SPDXRef-binary"
    },
    {
      "spdxElementId": "SPDXRef-port",
      "relationshipType": "CONTAINS",
      "relatedSpdxElement": "SPDXRef-file-0"
    },
    {
      "spdxElementId": "SPDXRef-port",
      "relationshipType": "CONTAINS",
      "relatedSpdxElement": "SPDXRef-file-1"
    },
    {
      "spdxElementId": "SPDXRef-binary",
      "relationshipType": "GENERATED_FROM",
      "relatedSpdxElement": "SPDXRef-port"
    },
    {
      "spdxElementId": "SPDXRef-file-0",
      "relationshipType": "CONTAINED_BY",
      "relatedSpdxElement": "SPDXRef-port"
    },
    {
      "spdxElementId": "SPDXRef-file-1",
      "relationshipType": "CONTAINED_BY",
      "relatedSpdxElement": "SPDXRef-port"
    }
  ],
  "packages": [
    {
      "name": "boost-tokenizer",
      "SPDXID": "SPDXRef-port",
      "versionInfo": "1.83.0",
      "downloadLocation": "git+https://github.com/Microsoft/vcpkg@05ada2a1cc63fe9b4f5b4e9ac1d6ec63961e281b",
      "homepage": "https://github.com/boostorg/tokenizer",
      "licenseConcluded": "BSL-1.0",
      "licenseDeclared": "NOASSERTION",
      "copyrightText": "NOASSERTION",
      "description": "Boost tokenizer module",
      "comment": "This is the port (recipe) consumed by vcpkg."
    },
    {
      "name": "boost-tokenizer:x64-osx",
      "SPDXID": "SPDXRef-binary",
      "versionInfo": "e2a9222c4641102f397f5eca33dfe55f6769eb7613fa7a9af4e394259a6d85fd",
      "downloadLocation": "NONE",
      "licenseConcluded": "BSL-1.0",
      "licenseDeclared": "NOASSERTION",
      "copyrightText": "NOASSERTION",
      "comment": "This is a binary package built by vcpkg."
    },
    {
      "SPDXID": "SPDXRef-resource-1",
      "name": "boostorg/tokenizer",
      "downloadLocation": "git+https://github.com/boostorg/tokenizer@boost-1.83.0",
      "licenseConcluded": "NOASSERTION",
      "licenseDeclared": "NOASSERTION",
      "copyrightText": "NOASSERTION",
      "checksums": [
        {
          "algorithm": "SHA512",
          "checksumValue": "25e3aca064a1aeff65cd9abd8e828a1a25c2f4411d8e66f1bda7bccb9fc30145923eb1ca79d9ae8328584305a4d88e517897b870d45eca17923038edc58619f5"
        }
      ]
    }
  ],
  "files": [
    {
      "fileName": ".//Users/vmetreveli/.vcpkg-clion/vcpkg/buildtrees/versioning_/versions/boost-tokenizer/05ada2a1cc63fe9b4f5b4e9ac1d6ec63961e281b/portfile.cmake",
      "SPDXID": "SPDXRef-file-0",
      "checksums": [
        {
          "algorithm": "SHA256",
          "checksumValue": "76737ec8256865f2ab35333f5874ccb63e6e37b5b26dea633137a45b2f131a47"
        }
      ],
      "licenseConcluded": "NOASSERTION",
      "copyrightText": "NOASSERTION"
    },
    {
      "fileName": ".//Users/vmetreveli/.vcpkg-clion/vcpkg/buildtrees/versioning_/versions/boost-tokenizer/05ada2a1cc63fe9b4f5b4e9ac1d6ec63961e281b/vcpkg.json",
      "SPDXID": "SPDXRef-file-1",
      "checksums": [
        {
          "algorithm": "SHA256",
          "checksumValue": "ca3eed3bc4993d60972d18d9d626ab8ea98debdce47c73426c35a56e3941181d"
        }
      ],
      "licenseConcluded": "NOASSERTION",
      "copyrightText": "NOASSERTION"
    }
  ]
}
